{
    "Actor": {
        "types": [
            "named",
            "mook"
        ],
        "templates": {
            "commonStats": {
                "species": {
                    "type": "String",
                    "label": "Species",
                    "value": ""
                },
                "shock": {
                    "type": "Number",
                    "label": "Shock",
                    "value": 0,
                    "max": 15,
                    "min": 0
                },
                "wounds": {
                    "type": "Number",
                    "label": "Wounds",
                    "value": 0,
                    "max": 15,
                    "min": 0
                },
                "quote": {
                    "type": "String",
                    "label": "Quote",
                    "value": ""
                },
                "downAndOut": {
                    "type": "Boolean",
                    "label": "Down and out",
                    "value": false
                }
            }
        },
        "named": {
            "templates": [
                "commonStats"
            ],
            "playerName": {
                "type": "String",
                "label": "Player Name",
                "value": ""
            },
            "exp": {
                "type": "Number",
                "label": "Experience",
                "total": 0,
                "spent": 0
            },
            "birthplace": {
                "type": "String",
                "label": "Birthplace",
                "value": ""
            },
            "family": {
                "mother": {
                    "type": "String",
                    "label": "Mother's Name",
                    "value": ""
                },
                "father": {
                    "type": "String",
                    "label": "Father's Name",
                    "value": ""
                },
                "siblings": []
            },
            "title": {
                "type": "String",
                "label": "Title",
                "value": ""
            },
            "age": {
                "type": "Number",
                "label": "Age",
                "value": 0
            },
            "faith": {
                "type": "String",
                "label": "Faith",
                "value": ""
            },
            "sex": {
                "type": "String",
                "label": "Sex",
                "value": ""
            },
            "gender": {
                "type": "String",
                "label": "Gender",
                "value": ""
            },
            "mainHand": {
                "type": "String",
                "label": "Main Hand",
                "value": "Right"
            },
            "goal": {
                "type": "String",
                "label": "Goal",
                "value": ""
            },
            "notes": {
                "type": "String",
                "label": "Notes",
                "value": "Notes"
            },
            "money": {
                "type": "Number",
                "label": "Money",
                "value": 0
            },
            "encumbranceLimit": {
                "type": "Float",
                "label": "Encumbrance limit",
                "value": 12.0
            }

        },
        "mook": {
            "templates": [
                "commonStats"
            ]
        }
    },
    "Item": {
        "types": [
            "ammunition",
            "armor",
            "disease",
            "genericItem",
            "skill",
            "spell",
            "trait",
            "weapon"
        ],
        "templates": {
            "itemDescription": {
                "description": {
                    "type": "String",
                    "label": "Description",
                    "value": "This is a description."
                }
            },
            "commonStats": {
                "availability": {
                    "type": "String",
                    "label": "Availability",
                    "value": ""
                },
                "trader": {
                    "type": "String",
                    "label": "Trader",
                    "value": ""
                },
                "tradeGroup": {
                    "type": "Number",
                    "label": "Trade Group",
                    "value": 1
                },
                "price": {
                    "type": "Number",
                    "label": "Price",
                    "value": 0
                },
                "weight": {
                    "type": "Float",
                    "label": "Weight",
                    "value": 0.0
                },
                "quantity": {
                    "type": "Number",
                    "label": "Quantity",
                    "value": 1
                }
            },
            "skillsTraits": {
                "skillCategory": {
                    "type": "String",
                    "label": "Category",
                    "value": ""
                },
                "skillLevel": {
                    "type": "Number",
                    "label": "Level",
                    "value": 0,
                    "min": 0,
                    "max": 12
                }
            }
        },
        "ammunition": {
            "templates": [
                "commonStats",
                "itemDescription"
            ],
            "ammoCount": 0,
            "ammoType": "",
            "slashDamage": 0,
            "pierceDamage": 0,
            "bluntDamage": 0,
            "energyDamage": 0,
            "shockDamage": 0
        },
        "armor": {
            "templates": [
                "commonStats",
                "itemDescription"
            ],
            "coverage": {
                "type": "String",
                "label": "Coverage",
                "value": "All"
            },
            "protection": {
                "slash": {
                    "type": "Number",
                    "label": "Slash Protection",
                    "value": 0
                },
                "pierce": {
                    "type": "Number",
                    "label": "Pierce Protection",
                    "value": 0
                },
                "blunt": {
                    "type": "Number",
                    "label": "Blunt Protection",
                    "value": 0
                },
                "energy": {
                    "type": "Number",
                    "label": "Energy Protection",
                    "value": 0
                },
                "shock": {
                    "type": "Number",
                    "label": "Shock Protection",
                    "value": 0
                }
            },
            "isShield": {
                "type": "Boolean",
                "label": "Is Shield?",
                "value": false
            },
            "blockValue": {
                "type": "Number",
                "label": "Blockvalue",
                "value": 0
            },
            "isEquipped": {
                "type": "Boolean",
                "label": "Is it equipped?",
                "value": false
            }
        },
        "skill": {
            "templates": [
                "skillsTraits",
                "itemDescription"
            ],
            "teacher": {
                "type": "Boolean",
                "label": "Teacher required",
                "value": false
            },
            "levelUp": {
                "type": "Boolean",
                "label": "Eligable for levelup",
                "value": false
            },
            "teachable": {
                "type": "Boolean",
                "label": "Recuires teacher",
                "value": false
            }
        },
        "trait": {
            "templates": [
                "skillsTraits",
                "itemDescription"
            ],
            "skillLevel": {
                "min": -4,
                "max": 4,
                "value": 0
            },
            "reversed": {
                "type": "Boolean",
                "label": "Reversed",
                "value": false
            }
        },
        "weapon": {
            "templates": [
                "commonStats",
                "itemDescription"
            ],
            "attackSkill": {
                "type": "String",
                "label": "Skill",
                "value": ""
            },
            "damage": {
                "slash": {
                    "type": "Number",
                    "label": "Slash Damage",
                    "value": 0
                },
                "pierce": {
                    "type": "Number",
                    "label": "Pierce Damage",
                    "value": 0
                },
                "blunt": {
                    "type": "Number",
                    "label": "Blunt Damage",
                    "value": 0
                },
                "energy": {
                    "type": "Number",
                    "label": "Energy Damage",
                    "value": 0
                },
                "shock": {
                    "type": "Number",
                    "label": "Shock Damage",
                    "value": 0
                }
            },
            "reach": {
                "type": "String",
                "label": "Reach",
                "value": "Normal"
            },
            "blockValue": {
                "type": "Number",
                "label": "Block",
                "value": 0
            },
            "isRanged": {
                "type": "Boolean",
                "label": "Ranged weapon?",
                "value": false
            },
            "consumesAmmo": {
                "type": "Boolean",
                "label": "Consumes ammo?",
                "value": false
            },
            "ammoGroup": {
                "type": "String",
                "label": "Ammo Group",
                "value": ""
            },
            "selectedAmmo": {
                "type": "String",
                "label": "Selected Ammo",
                "value": "No ammo selected"
            },
            "magazine": {
                "type": "Number",
                "label": "Magazine size",
                "value": 0
            },
            "ammoCount": {
                "type": "Number",
                "label": "Ammo count",
                "value": 0
            },
            "range": {
                "type": "Number",
                "label": "Range",
                "value": {
                    "rangeClose": 0,
                    "rangeNormal": 0,
                    "rangeLong": 0,
                    "rangeMax": 0
                }
            },
            "isEquipped": {
                "type": "Boolean",
                "label": "Is it equipped?",
                "value": false
            }
        },
        "genericItem": {
            "templates": [
                "commonStats",
                "itemDescription"
            ]
        }
    }
}